<?xml version="1.0" encoding="utf-8"?><SADER_Structure><Internal_ID /><Category>Bilateral</Category><Status>Published</Status><Languages>Arabic</Languages><Official_Gazette_Number /><Official_Gazette_Date /><Decree>Leb-LC-Ar_1999-06-14_00084_Law</Decree><Countries>تشيكيا</Countries><Keywords>حماية - إستثمار - مستثمر - أملاك منقولة - أملاك غير منقولة - شركة - مؤسسة - أسهم - عائدات - خسارة - تعويض - ملكية - تحويل حر</Keywords><IntoForce>Effective</IntoForce><UseLinksDB>1</UseLinksDB><links /><WebSiteitems /></SADER_Structure>