<?xml version="1.0" encoding="utf-8"?><MOFA_Structure><Internal_ID /><Category>Bilateral</Category><Status>Published</Status><Languages>Arabic</Languages><Official_Gazette_Number>12</Official_Gazette_Number><Official_Gazette_Date>09/03/2017</Official_Gazette_Date><Decree>Leb_LC-Ar_2017-02-24_00202_Marit</Decree><Countries /><Keywords>قدرات فنية - خطة عمل - استراتيجيات إصلاحية  - معلومات - اتصالات - سياسات معتمدة - شروط خاصة - قدرات إصلاحية.
</Keywords><IntoForce>Effective</IntoForce><UseLinksDB>1</UseLinksDB><links /><WebSiteitems /></MOFA_Structure>