<?xml version="1.0" encoding="utf-8"?><MOFA_Structure><Internal_ID /><Category>Bilateral</Category><Status>Published</Status><Languages>Arabic</Languages><Official_Gazette_Number>26</Official_Gazette_Number><Official_Gazette_Date>07/06/2018</Official_Gazette_Date><Decree>Leb_LC-Ar_2018-05-29_03202_Mar</Decree><Countries>مصر</Countries><Keywords>ثقافة - تعاون ثقافي - معرفة - تشريعات - خبرات -مؤسسات ثقافية - مكتبات - متاحف - دور نشر - مؤتمرات -ندوات - دورات تدريبية - ترجمة - معارض - فنون - زيارات </Keywords><IntoForce>Effective</IntoForce><UseLinksDB>1</UseLinksDB><links /><WebSiteitems /></MOFA_Structure>